txtar/__init__.py
txtar/txtar.py
txtar-0.1.1.dist-info/WHEEL
txtar-0.1.1.dist-info/METADATA
txtar-0.1.1.dist-info/RECORD
